pyproject.toml
setup.py
star_exceptions.py
starintel_doc.py
starintel_doc.egg-info/PKG-INFO
starintel_doc.egg-info/SOURCES.txt
starintel_doc.egg-info/dependency_links.txt
starintel_doc.egg-info/top_level.txt