Metadata-Version: 2.1
Name: starintel-doc
Version: 0.5.0
Summary: Document Spec for Star intel
Home-page: https://gitlab.com/unseen-giants/starintel_doc
Author: Nsaspy
License: MIT
Platform: UNKNOWN
Classifier: License :: OSI Approved :: MIT License
Classifier: Intended Audience :: Developers
Classifier: Natural Language :: English
Classifier: Programming Language :: Python :: 3 :: Only
Classifier: Programming Language :: Python :: 3.10
Classifier: Operating System :: OS Independent
